banregio_api-0.1.1.dist-info/METADATA
banregio_api-0.1.1.dist-info/RECORD
banregio_api-0.1.1.dist-info/WHEEL
banregio_api-0.1.1.dist-info/top_level.txt
banregioapi/__init__.py
banregioapi/banregio_api_helper.py
banregioapi/banregio_token_helper.py
banregioapi/resources/__init__.py
banregioapi/resources/account.py
banregioapi/resources/transaction.py
banregioapi/utils/__init__.py
banregioapi/utils/service.py
